{"is_source_file": true, "format": "TypeScript with React Native", "description": "This source file defines a React functional component 'Board' for rendering a Tic Tac Toe game board in a mobile app. It receives the game state and event handlers as props, displays individual cells, and optionally highlights a winning line.", "external_files": ["./Cell"], "external_methods": [], "published": ["default"], "classes": [], "methods": [{"name": "Board", "description": "React functional component that renders the Tic Tac Toe board with cells, handling user interaction and highlighting winning lines."}], "calls": ["React.createElement", "board.map", "Cell"], "search-terms": ["React", "Tic Tac Toe", "Board component", "cell rendering", "highlighting winning line", "TypeScript", "React Native styles"], "state": 2, "file_id": 10, "knowledge_revision": 42, "git_revision": "7ed4e7895e7534f8be3585c65541f97622e6e323", "revision_history": [{"22": ""}, {"42": "7ed4e7895e7534f8be3585c65541f97622e6e323"}], "ctags": [], "hash": "d0ebeb3391ff125949d6110d9915ec34", "format-version": 4, "code-base-name": "frontend", "filename": "frontend/src/components/Board.tsx"}