{"is_source_file": true, "format": "TypeScript/React Native", "description": "This file defines the main application component for a React Native project, including an error boundary component, styling, and rendering of the GameScreen component within the app.", "external_files": ["./src/screens/GameScreen", "./src/theme/colors"], "external_methods": ["React.Component", "React.PropsWithChildren", "React.ErrorInfo", "console.error", "StyleSheet.create"], "published": ["default"], "classes": [{"name": "ErrorBoundary", "description": "A React component that catches JavaScript errors anywhere in its child component tree and displays a fallback UI."}], "methods": [{"name": "ErrorBoundary.constructor", "description": "Initializes the ErrorBoundary component with default error state."}, {"name": "ErrorBoundary.getDerivedStateFromError", "description": "Updates state to indicate an error has occurred."}, {"name": "ErrorBoundary.componentDidCatch", "description": "Logs error details when an error is caught."}, {"name": "ErrorBoundary.render", "description": "Renders fallback UI if an error has occurred, or the children components otherwise."}, {"name": "App", "description": "Main application component that wraps the GameScreen with an error boundary and styles."}], "calls": ["React.createElement(React.StrictMode, ...)", "React.createElement(ErrorBoundary, ...)", "React.createElement(SafeAreaView, ...)", "React.createElement(StatusBar, ...)", "React.createElement(View, ...)", "React.createElement(GameScreen, ...)"], "search-terms": ["ErrorBoundary", "GameScreen", "react-native styles", "main app component", "TypeScript React Native app"], "state": 2, "file_id": 3, "knowledge_revision": 45, "git_revision": "3fdec2092a85259812a66c7198f38912ca78e173", "revision_history": [{"13": "06d861dd99cbb961c4d69b4a0754ee4644d980ef"}, {"14": "06d861dd99cbb961c4d69b4a0754ee4644d980ef"}, {"44": "7ed4e7895e7534f8be3585c65541f97622e6e323"}, {"45": "3fdec2092a85259812a66c7198f38912ca78e173"}], "ctags": [], "hash": "601ee68dfc91ebc42aec935102dab91a", "format-version": 4, "code-base-name": "frontend", "filename": "frontend/App.tsx"}